ndpulsegen/.DS_Store
ndpulsegen/__init__.py
ndpulsegen/comms.py
ndpulsegen/compiler.py
ndpulsegen/console_read.py
ndpulsegen/transcode.py
ndpulsegen-1.0.1.dist-info/METADATA
ndpulsegen-1.0.1.dist-info/WHEEL
ndpulsegen-1.0.1.dist-info/licenses/LICENSE
ndpulsegen-1.0.1.dist-info/RECORD
