Metadata-Version: 2.1
Name: ndpulsegen
Version: 1.0.1
Summary: A package to interface with the Narwhal Devices Pulse Generator
Project-URL: Homepage, https://github.com/RorySpeirs/narwhaldevs-pulsegen
Project-URL: Device manufacturer, https://www.narwhaldevices.com
Author-email: Rory Speirs <rory@narwhaldevices.com>
License-File: LICENSE
Classifier: License :: OSI Approved :: MIT License
Classifier: Operating System :: OS Independent
Classifier: Programming Language :: Python :: 3
Requires-Python: >=3.7
Requires-Dist: numpy
Requires-Dist: pyserial
